MAVez/__init__.py
MAVez/controller.py
MAVez/coordinate.py
MAVez/enums.py
MAVez/flight_controller.py
MAVez/mission.py
MAVez/mission_item.py
MAVez/safe_logger.py
MAVez/translate_message.py
mavez-3.5.1.dist-info/licenses/LICENSE
mavez-3.5.1.dist-info/METADATA
mavez-3.5.1.dist-info/WHEEL
mavez-3.5.1.dist-info/top_level.txt
mavez-3.5.1.dist-info/RECORD
