Metadata-Version: 2.4
Name: MAVez
Version: 3.5.1
Summary: An intuitive MAVLink library for ArduPilot via pymavlink
Author-email: The Pennsylvania State University Unmanned Aerial Systems Club <psuuasofficial@gmail.com>
License-Expression: GPL-3.0
Project-URL: Homepage, https://github.com/UnmannedAerialSystems/MAVez
Keywords: MAVLink,ArduPilot,UAS,Drone,pymavlink,MAVez
Classifier: Development Status :: 4 - Beta
Classifier: Intended Audience :: Developers
Classifier: Programming Language :: Python :: 3
Classifier: Topic :: Scientific/Engineering
Classifier: Operating System :: OS Independent
Classifier: Natural Language :: English
License-File: LICENSE
Requires-Dist: pymavlink>=2.4.0
Requires-Dist: pyparsing>=3.2.4
Requires-Dist: colorlog>=6.9.0
Requires-Dist: datetime>=5.5
Requires-Dist: uas-messenger>=1.1.0
Provides-Extra: docs
Requires-Dist: sphinx>=4.0.0; extra == "docs"
Requires-Dist: furo; extra == "docs"
Requires-Dist: sphinx-autodoc-typehints; extra == "docs"
Requires-Dist: pymavlink>=2.4.0; extra == "docs"
Dynamic: license-file
